image_processor/__init__.py
image_processor/core.py
image_processor_luisa-0.1.0.dist-info/licenses/LICENSE
image_processor_luisa-0.1.0.dist-info/METADATA
image_processor_luisa-0.1.0.dist-info/WHEEL
image_processor_luisa-0.1.0.dist-info/top_level.txt
image_processor_luisa-0.1.0.dist-info/RECORD
