Metadata-Version: 2.4
Name: image-processor-luisa
Version: 0.1.0
Summary: Pacote simples de processamento de imagens com Pillow
Home-page: https://github.com/seuusuario/image-processor
Author: Luísa
Author-email: seu@email.com
Classifier: Programming Language :: Python :: 3
Classifier: License :: OSI Approved :: MIT License
Classifier: Operating System :: OS Independent
Requires-Python: >=3.6
License-File: LICENSE
Requires-Dist: Pillow>=9.0.0
Dynamic: author
Dynamic: author-email
Dynamic: classifier
Dynamic: description
Dynamic: description-content-type
Dynamic: home-page
Dynamic: license-file
Dynamic: requires-dist
Dynamic: requires-python
Dynamic: summary
